{
  "slug": "iphone-arka-kamera-tamiri",
  "marka": "iphone",
  "markaLabel": "iPhone",
  "tamirKey": "arka-kamera-tamiri",
  "tamirLabel": "Arka Kamera Tamiri",
  "title": "iPhone Arka Kamera Tamiri",
  "metaDescription": "Trabzon'da iPhone arka kamera tamiri için Vip İletişim Teknik Servis. Orijinal parça, aynı gün teslim, 90 gün garanti. Ücretsiz ön inceleme için arayın.",
  "icerik": "## iPhone Arka Kamera Tamiri\n\nPro modellerde üç, standart modellerde iki lens — ana, ultra geniş ve telephoto — birbirinden bağımsız çalışır. Birinin arızalanması diğerlerini etkilemez; bu yüzden Vip İletişim Trabzon önce hangi lensin sorunlu olduğunu izole eder, sonra yalnızca onu değiştirir.\n\nCinematic Mode aniden çalışmayı bırakıyorsa veya odak sürekli kayıyorsa, OIS (optik görüntü sabitleme) mekanizması şüphelidir. Belirli bir zoom seviyesinde (örneğin 3x telephoto) görüntü gelmiyorsa, o lensin modülü arızalanmış demektir. Pro modellerde LiDAR mesafe ölçümü bozulmuşsa bu da ayrıca test edilir.\n\nÖnce her lens tek tek farklı ışık koşullarında test edilir; bu, gereksiz parça değişimini önler. Yalnızca arızalı modül sökülüp orijinal kalitede yenisiyle değiştirilir. Diğer lensler ve LiDAR (varsa) bu sırada hiç açılmaz.\n\nTeslim öncesi Cinematic Mode, ProRAW ve OIS performansı son kez doğrulanır. [Ücretsiz ön inceleme](/iletisim) sonrası hangi lensin etkilendiği netleşir, fiyat ona göre belirlenir.",
  "sss": [
    {
      "soru": "Üç lens de mi değişiyor?",
      "cevap": "Hayır, yalnızca arızalı modül değiştirilir; diğerlerine dokunulmaz."
    },
    {
      "soru": "Cinematic Mode çalışmıyor, bu kamera arızası mı?",
      "cevap": "Genelde evet, OIS mekanizmasından kaynaklanır; ön incelemede kesinleşir."
    },
    {
      "soru": "Ne kadar sürer?",
      "cevap": "Genellikle 45-60 dakika; Pro modellerde LiDAR testi nedeniyle biraz uzayabilir."
    },
    {
      "soru": "Fiyat neye göre?",
      "cevap": "Hangi lensin (ana, ultra geniş, telephoto) arızalı olduğuna göre değişir."
    },
    {
      "soru": "Garanti var mı?",
      "cevap": "Evet, işçilik garantisi sunuyoruz."
    },
    {
      "soru": "Orijinal Apple parçası mı kullanılıyor?",
      "cevap": "Talebinize göre orijinal veya sertifikalı OEM kalitesinde modül kullanılabilir."
    }
  ],
  "desteklenenModeller": [
    {
      "model": "iPhone X",
      "aktif": true
    },
    {
      "model": "iPhone XS",
      "aktif": true
    },
    {
      "model": "iPhone XS Max",
      "aktif": true
    },
    {
      "model": "iPhone XR",
      "aktif": true
    },
    {
      "model": "iPhone 11",
      "aktif": true
    },
    {
      "model": "iPhone 11 Pro",
      "aktif": true
    },
    {
      "model": "iPhone 11 Pro Max",
      "aktif": true
    },
    {
      "model": "iPhone SE (2. Nesil)",
      "aktif": true
    },
    {
      "model": "iPhone 12 mini",
      "aktif": true
    },
    {
      "model": "iPhone 12",
      "aktif": true
    },
    {
      "model": "iPhone 12 Pro",
      "aktif": true
    },
    {
      "model": "iPhone 12 Pro Max",
      "aktif": true
    },
    {
      "model": "iPhone 13 mini",
      "aktif": true
    },
    {
      "model": "iPhone 13",
      "aktif": true
    },
    {
      "model": "iPhone 13 Pro",
      "aktif": true
    },
    {
      "model": "iPhone 13 Pro Max",
      "aktif": true
    },
    {
      "model": "iPhone SE (3. Nesil)",
      "aktif": true
    },
    {
      "model": "iPhone 14",
      "aktif": true
    },
    {
      "model": "iPhone 14 Plus",
      "aktif": true
    },
    {
      "model": "iPhone 14 Pro",
      "aktif": true
    },
    {
      "model": "iPhone 14 Pro Max",
      "aktif": true
    },
    {
      "model": "iPhone 15",
      "aktif": true
    },
    {
      "model": "iPhone 15 Plus",
      "aktif": true
    },
    {
      "model": "iPhone 15 Pro",
      "aktif": true
    },
    {
      "model": "iPhone 15 Pro Max",
      "aktif": true
    },
    {
      "model": "iPhone 16",
      "aktif": true
    },
    {
      "model": "iPhone 16 Plus",
      "aktif": true
    },
    {
      "model": "iPhone 16 Pro",
      "aktif": true
    },
    {
      "model": "iPhone 16 Pro Max",
      "aktif": true
    },
    {
      "model": "iPhone 17",
      "aktif": true
    },
    {
      "model": "iPhone 17 Slim",
      "aktif": true
    },
    {
      "model": "iPhone 17 Pro",
      "aktif": true
    },
    {
      "model": "iPhone 17 Pro Max",
      "aktif": true
    },
    {
      "model": "iPhone 18",
      "aktif": true
    },
    {
      "model": "iPhone 18 Air",
      "aktif": true
    },
    {
      "model": "iPhone 18 Pro",
      "aktif": true
    },
    {
      "model": "iPhone 18 Pro Max",
      "aktif": true
    }
  ]
}
